fastfit/__init__.py
fastfit/modeling.py
fastfit/train.py
fastfit/utils.py
fast_fit-1.2.1.dist-info/LICENSE
fast_fit-1.2.1.dist-info/METADATA
fast_fit-1.2.1.dist-info/WHEEL
fast_fit-1.2.1.dist-info/entry_points.txt
fast_fit-1.2.1.dist-info/top_level.txt
fast_fit-1.2.1.dist-info/RECORD
