Metadata-Version: 2.1
Name: fast-fit
Version: 1.2.1
Summary: Fast and effective approach for few shot with many classes
Home-page: https://github.com/IBM/fastfit
Author: Elron Bandel & Asaf Yehudai
Author-email: elron.bandel@ibm.com
License: Apache 2.0
Project-URL: Source, https://github.com/IBM/fastfit/
Keywords: text classification machine learning NLP
Classifier: Development Status :: 4 - Beta
Classifier: Intended Audience :: Developers
Classifier: Topic :: Text Processing
Classifier: Topic :: Scientific/Engineering :: Artificial Intelligence
Classifier: License :: OSI Approved :: Apache Software License
Classifier: Programming Language :: Python :: 3
Classifier: Programming Language :: Python :: 3.7
Classifier: Programming Language :: Python :: 3.8
Classifier: Programming Language :: Python :: 3.9
License-File: LICENSE
Requires-Dist: torch
Requires-Dist: transformers[torch]
Requires-Dist: scikit-learn
Requires-Dist: datasets
Provides-Extra: dev
Requires-Dist: check-manifest ; extra == 'dev'
Requires-Dist: pytest ; extra == 'dev'
Provides-Extra: test
Requires-Dist: coverage ; extra == 'test'
